{"tokens": ["<|endoftext|>", "**", " Dis", "claimer", ":", " I", " am", " not", " an", " expert", ",", " just", " someone", " trying", " to", " become", " better", " at", " blogging", " by", " writing", " about", " it", ".", "\n", "Just", " like", " a", " business", ",", " your", " blog", " has", " consumed", " all", " of", " your", " past", " time", ".", " Yet", " you", " tire", "lessly", " keep", " keeping", " on", ",", " because", " you", " love", " what", " you", " do", ".", "\n", "Also", " just", " like", " a", " business", ",", " your", " blog", " needs", " a", " plan", ".", " I", "'m", " not", " talking", " about", " a", " formal", " write", " up", " like", " business", " plans", " from", " management", " classes", ".", " I", "'m", " talking", " about", " a", " simple", ",", " immediate", " plan", " that", " includes", " precise", " and", " attain", "able", " goals", " of", " what", ",", " when", ",", " how", " and", " for", " how", " long", ".", "\n", "Go", "al", " 1", ":", " Increase", " page", " views", " from", " 100", " to", " 400", " visitors", " per", " day", ".", "\n", "How", "?", " Exposure", " through", " commenting", " on", " other", " blogs", ",", " and", " connecting", " via", " G", "FC", " or", " Bl", "ogl", "ov", "in", ".", "\n", "How", " much", "?", " Each", " day", ",", " comment", " for", " two", " hours", " and", " add", " five", " connections", ".", "\n", "For", " how", " long", "?", " Two", " months", ".", "\n", "Go", "al", " 2", ":", " Post", " at", " least", " three", " times", " per", " week", ".", "\n", "How", "?", " Create", " \"", "week", "ly", " series", "\"", " and", " set", " up", " a", " day", " of", " the", " week", " to", " post", " on", " each", " series", ".", "\n", "For", " example", ",", " \"", "H", "ump", " Day", " Hun", "ks", "\"", " happens", " every", " Wednesday", ".", " So", " I", " have", " a", " guaranteed", " post", " on", " that", " day", ".", "\n", "How", " much", "?", " Three", " times", " a", " week", ".", "\n", "Sunday", " night", " --", " \"", "Week", "ends", " in", " Seattle", ".\"", "\n", "Wednesday", " --", " \"", "H", "ump", " Day", " Hun", "ks", ".\"", "\n", "Friday", " --", " \"", "Friday", " Girl", " Cr", "ush", ".\"", "\n", "For", " how", " long", "?", " As", " long", " as", " the", " blog", " exists", ".", "\n", "In", "cluding", " the", " results", " above", ",", " I", " also", " started", " getting", " more", " sponsored", " posts", ",", " sponsors", ",", " companies", " asking", " for", " product", " reviews", ",", " and", " best", " of", " all", ",", " new", " followers", " of", " my", " own", ".", "\n", "As", " you", " can", " see", ",", " having", " a", " plan", " gives", " you", " goals", " to", " strive", " for", ",", " and", " keeps", " you", " both", " entertained", " and", " challenged", ".", " Plus", ",", " the", " sweet", " success", " of", " achieving", " something", " --", " small", " or", " large", " --", " feels", " so", " fulfilling", ".", "\n", "So", ",", " what", " is", " the", " plan", " for", " your", " blog", "?", "\n", "Good", " job", "!!", " Cong", "r", "ats", " on", " reaching", " all", " your", " goals", "!", "\n", "Aw", "esome", " goals", " and", " results", ",", " darling", "!", "\n", "I", " can", "'t", " say", " I", " have", " any", " plans", ".", " I", "'ve", " just", " started", " out", " though", ".", " I", " plan", " to", " post", " something", " pretty", " much", " everyday", " and", " have", " been", " consistent", " with", " this", " so", " far", ".", " You", "'ve", " got", " me", " thinking", " though", ".", " Maybe", " I", " will", " make", " some", " goals", ".", " But", " not", " just", " yet", ",", " it", "'s", " a", " bit", " too", " early", ".", "\n", "w", "ow", "!", " that", "'s", " a", " good", " goal", " you", " have", " in", " there", "!", " i", "'m", " inspired", ".", "\n", "Great", " job", " on", " all", " of", " your", " success", "!", " Thanks", " for", " the", " tips", "!", "\n", "Hi", " girl", ",", " thanks", " you", " so", " much", ".", " your", " the", " only", " one", " who", " often", " comment", " to", " me", " and", " I", " bless", " to", " have", " you", " as", " a", " new", " friend", " here", ".."], "values": [[0.0, -0.024321231991052628, -0.08948001265525818, 0.44584012031555176, 0.2718062996864319], [0.0, -0.023740777745842934, 0.10945740342140198, -0.6201467514038086, -0.21689513325691223], [-0.23504294455051422, 0.061262376606464386, -0.23504294455051422, -0.9048197269439697, -0.26064333319664], [-1.1628954410552979, 0.32188692688941956, -1.1628954410552979, -1.4058187007904053, -0.2767978310585022], [-0.5536244511604309, 0.08506380021572113, -0.5536244511604309, -2.8737564086914062, -0.15364892780780792], [-0.5990632176399231, 0.15426217019557953, -0.5990632176399231, -0.875601053237915, -0.2575056552886963], [-1.3822014331817627, 0.27904850244522095, -1.3822014331817627, -0.552783727645874, -0.20188699662685394], [-1.2131589651107788, 0.12219242006540298, -1.2131589651107788, -0.22712837159633636, -0.10072251409292221], [-0.44417157769203186, 0.10964756458997726, -0.44417157769203186, -0.7917249798774719, -0.24685858190059662], [-1.8556239604949951, 0.5042551159858704, -1.8556239604949951, -1.0424656867980957, -0.2717442512512207], [-1.0386773347854614, 0.23261314630508423, -1.0386773347854614, -2.153733968734741, -0.2239513099193573], [-1.629868984222412, 0.2802394926548004, -1.629868984222412, -0.43851640820503235, -0.1719398945569992], [-1.9859930276870728, 0.3957223892211914, -1.9859930276870728, -0.5417977571487427, -0.19925668835639954], [-1.1066573858261108, 0.29925456643104553, -1.1066573858261108, -1.56935453414917, -0.27041301131248474], [-0.7644296884536743, 0.21191814541816711, -0.7644296884536743, -1.1741664409637451, -0.2772238552570343], [-0.8770802021026611, 0.23324917256832123, -0.8770802021026611, -0.9616014361381531, -0.26593825221061707], [-1.5728365182876587, 0.4109277129173279, -1.5728365182876587, -0.910949170589447, -0.261265367269516], [-0.7822238206863403, 0.21559366583824158, -0.7822238206863403, -1.1222050189971924, -0.2756163477897644], [-1.4656789302825928, 0.3667701780796051, -1.4656789302825928, -0.8163198232650757, -0.2502391040325165], [-0.877600908279419, 0.24246613681316376, -0.877600908279419, -1.1411466598510742, -0.2762829065322876], [-1.3355909585952759, 0.1852264702320099, -1.3355909585952759, -0.3319723606109619, -0.13868503272533417], [-1.1656129360198975, 0.3212704360485077, -1.1656129360198975, -1.1223971843719482, -0.2756235897541046], [-1.8063993453979492, 0.31965208053588867, -1.8063993453979492, -0.4562036991119385, -0.17695538699626923], [-0.9191206693649292, 0.14817339181900024, -0.9191206693649292, -2.7925124168395996, -0.16121211647987366], [-0.43207287788391113, 0.07616026699542999, -0.43207287788391113, -2.6356749534606934, -0.17626717686653137], [-1.2565739154815674, 0.2139100581407547, -1.2565739154815674, -0.43260765075683594, -0.17023277282714844], [-1.09990394115448, 0.2318490445613861, -1.09990394115448, -2.2878403663635254, -0.2107902616262436], [-0.529008150100708, 0.13197021186351776, -0.529008150100708, -0.810562014579773, -0.24946726858615875], [-1.2487026453018188, 0.3093930780887604, -1.2487026453018188, -1.8933236598968506, -0.24777162075042725], [-0.6780208349227905, 0.06831055134534836, -0.6780208349227905, -3.52640700340271, -0.10074993222951889], [-0.7291916608810425, 0.17742006480693817, -0.7291916608810425, -0.7674844861030579, -0.2433106154203415], [-1.324458360671997, 0.2972693145275116, -1.324458360671997, -0.6577080488204956, -0.22444593906402588], [-0.8692110776901245, 0.239717036485672, -0.8692110776901245, -1.126805305480957, -0.2757869064807892], [-1.098002552986145, 0.21882939338684082, -1.098002552986145, -0.541967511177063, -0.1992977112531662], [-0.5980935096740723, 0.13372057676315308, -0.5980935096740723, -2.157592535018921, -0.2235780507326126], [-0.6693054437637329, 0.18347297608852386, -0.6693054437637329, -1.4879508018493652, -0.2741244435310364], [-0.8367418646812439, 0.2171311378479004, -0.8367418646812439, -0.8938223719596863, -0.25949597358703613], [-1.40041983127594, 0.3544585704803467, -1.40041983127594, -0.8385553359985352, -0.25310879945755005], [-1.675270676612854, 0.4641158878803253, -1.675270676612854, -1.395960807800293, -0.2770393490791321], [-1.2775650024414062, 0.22641685605049133, -1.2775650024414062, -2.6258668899536133, -0.17722530663013458], [-1.5861194133758545, 0.3743880093097687, -1.5861194133758545, -2.0258777141571045, -0.23604024946689606], [-1.3269963264465332, 0.36837032437324524, -1.3269963264465332, -1.1909328699111938, -0.2775970995426178], [-1.0771219730377197, 0.24029791355133057, -1.0771219730377197, -0.6507607698440552, -0.22309257090091705], [-1.2288973331451416, 0.0035821825731545687, -1.2288973331451416, -0.0058470070362091064, -0.002914956770837307], [-1.0703153610229492, 0.06098856404423714, -1.0703153610229492, -0.12131315469741821, -0.05698186531662941], [-0.5525255799293518, 0.06289615482091904, -0.5525255799293518, -0.2617231607437134, -0.11383391916751862], [-1.5177439451217651, 0.19760967791080475, -1.5177439451217651, -0.3072251081466675, -0.1301996111869812], [-1.6601738929748535, 0.45733341574668884, -1.6601738929748535, -1.118455171585083, -0.2754732072353363], [-1.1882882118225098, 0.22314727306365967, -1.1882882118225098, -2.518693447113037, -0.18778884410858154], [-1.1313135623931885, 0.31360846757888794, -1.1313135623931885, -1.1734914779663086, -0.2772073745727539], [-0.7871711254119873, 0.2186734527349472, -0.7871711254119873, -1.20147705078125, -0.27779659628868103], [-0.36835843324661255, 0.10123381018638611, -0.36835843324661255, -1.1025488376617432, -0.27482420206069946], [-1.110217571258545, 0.0409417524933815, -1.110217571258545, -0.07669401168823242, -0.036877233535051346], [-1.6829913854599, 0.046487659215927124, -1.6829913854599, -0.056860193610191345, -0.02762204222381115], [-1.3325965404510498, 0.27140551805496216, -1.3325965404510498, -2.359402656555176, -0.20366668701171875], [-0.5767415761947632, 0.11684136837720871, -0.5767415761947632, -2.3702054023742676, -0.2025887668132782], [-1.4090065956115723, 0.30964547395706177, -1.4090065956115723, -2.196824550628662, -0.21976155042648315], [-1.337151050567627, 0.32089245319366455, -1.337151050567627, -0.7459927797317505, -0.23998220264911652], [-1.4201476573944092, 0.39175182580947876, -1.4201476573944092, -1.1286263465881348, -0.27585288882255554], [-0.9200839996337891, 0.20862233638763428, -0.9200839996337891, -0.6697338819503784, -0.2267427146434784], [-1.3522590398788452, 0.14047572016716003, -1.3522590398788452, -3.481738328933716, -0.10388226062059402], [-1.0089316368103027, 0.061242420226335526, -1.0089316368103027, -4.229414939880371, -0.06070026755332947], [-1.0710391998291016, 0.29634949564933777, -1.0710391998291016, -1.1543841361999512, -0.2766934037208557], [-1.431598424911499, 0.39543548226356506, -1.431598424911499, -1.1392244100570679, -0.27621954679489136], [-1.035172462463379, 0.27962636947631836, -1.035172462463379, -1.574897050857544, -0.2701253890991211], [-0.4590001106262207, 0.12402284890413284, -0.4590001106262207, -1.0181128978729248, -0.2702022194862366], [-1.5515797138214111, 0.4289607107639313, -1.5515797138214111, -1.418285608291626, -0.27646708488464355], [-1.4948371648788452, 0.30839505791664124, -1.4948371648788452, -2.33292293548584, -0.2063068002462387], [-0.8190703392028809, 0.10167034715414047, -0.8190703392028809, -0.29002195596694946, -0.12412896007299423], [-1.3989332914352417, 0.2554659843444824, -1.3989332914352417, -0.4767874777317047, -0.18261484801769257], [-1.2876074314117432, 0.19693295657634735, -1.2876074314117432, -0.37561529874801636, -0.152944877743721], [-1.8133684396743774, 0.3166408836841583, -1.8133684396743774, -0.4478871822357178, -0.17461475729942322], [-1.5351969003677368, 0.4274594485759735, -1.5351969003677368, -1.293682336807251, -0.2784394919872284], [-0.9684078693389893, 0.24392659962177277, -0.9684078693389893, -0.8288993835449219, -0.2518841624259949], [-1.1888270378112793, 0.2961059510707855, -1.1888270378112793, -0.8076620101928711, -0.2490740418434143], [-1.3100303411483765, 0.29089823365211487, -1.3100303411483765, -0.6454988718032837, -0.22205457091331482], [-2.224921703338623, 0.36573198437690735, -2.224921703338623, -0.41275277733802795, -0.16437971591949463], [-1.4521043300628662, 0.2797948122024536, -1.4521043300628662, -2.469484329223633, -0.19268231093883514], [-1.2312381267547607, 0.25748729705810547, -1.2312381267547607, -0.5842205286026001, -0.20912876725196838], [-1.8637399673461914, 0.48453983664512634, -1.8637399673461914, -0.8984389305114746, -0.25998252630233765], [-1.5624632835388184, 0.26519811153411865, -1.5624632835388184, -0.4308805763721466, -0.1697307825088501], [-1.0223472118377686, 0.1537635624408722, -1.0223472118377686, -0.36762988567352295, -0.1504024863243103], [-1.974591851234436, 0.5009112358093262, -1.974591851234436, -0.843136727809906, -0.2536783814430237], [-1.5866628885269165, 0.25299423933029175, -1.5866628885269165, -2.8112661838531494, -0.15945053100585938], [-0.9533147215843201, 0.16037526726722717, -0.9533147215843201, -0.42574161291122437, -0.1682290881872177], [-1.4973974227905273, 0.36674317717552185, -1.4973974227905273, -0.7782999277114868, -0.24492040276527405], [-1.7330269813537598, 0.46680140495300293, -1.7330269813537598, -1.0058035850524902, -0.2693561017513275], [-1.5649821758270264, 0.4319254159927368, -1.5649821758270264, -1.4345602989196777, -0.27599382400512695], [-0.8984550833702087, 0.1588917225599289, -0.8984550833702087, -0.45582661032676697, -0.17684993147850037], [-0.9497781991958618, 0.0621260404586792, -0.9497781991958618, -0.14070484042167664, -0.06541110575199127], [-1.0118811130523682, 0.16328862309455872, -1.0118811130523682, -0.4027790427207947, -0.1613713502883911], [-0.9899889826774597, 0.03159858658909798, -0.9899889826774597, -0.06601439416408539, -0.03191811963915825], [-1.781041145324707, 0.3860591948032379, -1.781041145324707, -0.6195015907287598, -0.21676039695739746], [-1.0577313899993896, 0.2860378324985504, -1.0577313899993896, -1.569106936454773, -0.2704257667064667], [-1.2871320247650146, 0.3326718509197235, -1.2871320247650146, -0.8842079639434814, -0.25845977663993835], [-0.9973373413085938, 0.14878647029399872, -0.9973373413085938, -0.3638346195220947, -0.14918369054794312], [-0.8660411834716797, 0.07535242289304733, -0.8660411834716797, -0.1924838125705719, -0.08700789511203766], [0.0, -0.005542032886296511, -0.5807367563247681, 0.018907472491264343, 0.009543106891214848], [-0.8564510941505432, 0.033370696008205414, -0.8564510941505432, -0.08122476935386658, -0.0389639250934124], [-1.5196709632873535, 0.370298832654953, -1.5196709632873535, -0.7698764801025391, -0.24367040395736694], [-0.8409134149551392, 0.22456099092960358, -0.8409134149551392, -0.9750778079032898, -0.2670441269874573], [-0.7069911956787109, 0.16263239085674286, -0.7069911956787109, -2.0901808738708496, -0.23003454506397247], [-1.5945494174957275, 0.4391036331653595, -1.5945494174957275, -1.116010069847107, -0.27537786960601807], [-1.2995685338974, 0.32519611716270447, -1.2995685338974, -1.8638150691986084, -0.250233918428421], [-1.2422709465026855, 0.18730948865413666, -1.2422709465026855, -0.36880946159362793, -0.15077990293502808], [-1.2770798206329346, 0.3535899519920349, -1.2770798206329346, -1.4027962684631348, -0.27687379717826843], [-1.1951937675476074, 0.2901102900505066, -1.1951937675476074, -0.7636586427688599, -0.2427307665348053], [-0.8955284357070923, 0.036934372037649155, -0.8955284357070923, -0.08619904518127441, -0.04124310240149498], [-0.996159553527832, 0.1740659475326538, -0.996159553527832, -0.4483189284801483, -0.17473702132701874], [-1.1315040588378906, 0.3003532886505127, -1.1315040588378906, -1.6561627388000488, -0.2654460668563843], [-1.3903615474700928, 0.35017359256744385, -1.3903615474700928, -1.843920350074768, -0.2518579363822937], [-0.6980832815170288, 0.15994760394096375, -0.6980832815170288, -2.099782943725586, -0.22912395000457764], [-1.1574578285217285, 0.11213227361440659, -1.1574578285217285, -0.21726597845554352, -0.0968780666589737], [-1.0860342979431152, 0.20164412260055542, -1.0860342979431152, -0.4881962835788727, -0.18567012250423431], [-1.3436999320983887, 0.3669915199279785, -1.3436999320983887, -1.0669214725494385, -0.27312013506889343], [-0.9673515558242798, 0.23624807596206665, -0.9673515558242798, -1.9346781969070435, -0.2442215234041214], [-0.8326244354248047, 0.23102347552776337, -0.8326244354248047, -1.3764616250991821, -0.27746421098709106], [-0.9563332796096802, 0.20372174680233002, -0.9563332796096802, -0.6019272208213806, -0.21302379667758942], [-1.3938698768615723, 0.37581291794776917, -1.3938698768615723, -1.0095491409301758, -0.26961836218833923], [-1.227352499961853, 0.012085197493433952, -1.227352499961853, -0.019890934228897095, -0.00984655786305666], [-1.3851079940795898, 0.3730070888996124, -1.3851079940795898, -1.0049842596054077, -0.2692981958389282], [-1.0030014514923096, 0.11644379049539566, -1.0030014514923096, -0.2678493857383728, -0.11609533429145813], [-1.552499532699585, 0.427062064409256, -1.552499532699585, -1.108629822731018, -0.2750803232192993], [-1.3756554126739502, 0.32985517382621765, -1.3756554126739502, -0.744724690914154, -0.23978038132190704], [-1.046549677848816, 0.25700342655181885, -1.046549677848816, -0.7827631831169128, -0.24557211995124817], [-1.1853607892990112, 0.2952144145965576, -1.1853607892990112, -0.8074876070022583, -0.24905025959014893], [-1.082871913909912, 0.2772022485733032, -1.082871913909912, -0.8623555302619934, -0.2559880316257477], [-0.651896059513092, 0.07552478462457657, -0.651896059513092, -0.26719334721565247, -0.11585403233766556], [-0.9520121216773987, 0.25734463334083557, -0.9520121216773987, -1.0198278427124023, -0.27031654119491577], [-1.1597965955734253, 0.28598490357398987, -1.1597965955734253, -1.90732741355896, -0.24658195674419403], [-1.7580740451812744, 0.36854296922683716, -1.7580740451812744, -0.5864606499671936, -0.20962880551815033], [-0.9772762060165405, 0.13157407939434052, -0.9772762060165405, -0.32005026936531067, -0.13463346660137177], [0.0, -0.008006604388356209, -1.4989196062088013, 0.01062670350074768, 0.005341583397239447], [-0.8536850214004517, 0.17900197207927704, -0.8536850214004517, -0.5866973400115967, -0.20968151092529297], [-0.9194778203964233, 0.1989569365978241, -0.9194778203964233, -0.61768639087677, -0.21638035774230957], [-1.7367451190948486, 0.4711496829986572, -1.7367451190948486, -1.0348902940750122, -0.2712831497192383], [-1.0391192436218262, 0.26209408044815063, -1.0391192436218262, -0.8315777778625488, -0.25222715735435486], [-1.1326814889907837, 0.2233196645975113, -1.1326814889907837, -0.5331932306289673, -0.19716015458106995], [0.0, -1.1465710401535034, -1.7042150497436523, 0.936512291431427, 0.6727854013442993], [-0.7804723978042603, 0.15341182053089142, -0.7804723978042603, -0.5307652950286865, -0.1965627819299698], [-0.06078774482011795, 0.015474926680326462, -0.06078774482011795, -0.8504558801651001, -0.25457313656806946], [-1.4642058610916138, 0.09003983438014984, -1.4642058610916138, -0.1316399872303009, -0.061493970453739166], [-0.9895128607749939, 0.20050080120563507, -0.9895128607749939, -0.5559087991714478, -0.20262576639652252], [0.0, -0.004550505429506302, -0.24076583981513977, 0.03711169958114624, 0.018900129944086075], [-0.14676780998706818, 0.015657465904951096, -0.14676780998706818, -0.2426627278327942, -0.10668188333511353], [0.0, -0.0303211472928524, -0.47349637746810913, 0.12078745663166046, 0.06403670459985733], [-1.5068814754486084, 0.296482652425766, -1.5068814754486084, -0.5315351486206055, -0.19675247371196747], [-1.0215259790420532, 0.27274850010871887, -1.0215259790420532, -1.6307131052017212, -0.26700103282928467], [0.0, -0.07032288610935211, -0.7603522539138794, 0.17047818005084991, 0.09248724579811096], [-1.236635684967041, 0.04691004380583763, -1.236635684967041, -0.07898488640785217, -0.037933599203825], [-1.3687093257904053, 0.13059213757514954, -1.3687093257904053, -0.2135382890701294, -0.09541261196136475], [-1.4049177169799805, 0.39098677039146423, -1.4049177169799805, -1.239778995513916, -0.2782987058162689], [-0.8811120986938477, 0.1923181414604187, -0.8811120986938477, -0.6267654895782471, -0.2182675153017044], [-0.9994391798973083, 0.16158254444599152, -0.9994391798973083, -2.7876195907592773, -0.16167321801185608], [-1.3079850673675537, 0.2589694559574127, -1.3079850673675537, -2.416260242462158, -0.19799113273620605], [-1.5555932521820068, 0.08178839832544327, -1.5555932521820068, -0.11134658753871918, -0.052576981484889984], [-0.81047523021698, 0.18219073116779327, -0.81047523021698, -0.6595159769058228, -0.22479493916034698], [-1.0539336204528809, 0.07373053580522537, -1.0539336204528809, -0.15134592354297638, -0.06995747238397598], [-1.5643796920776367, 0.13693322241306305, -1.5643796920776367, -0.19378089904785156, -0.08753196150064468], [-1.1579028367996216, 0.32134509086608887, -1.1579028367996216, -1.1873608827590942, -0.27752336859703064], [-1.0055572986602783, 0.07046974450349808, -1.0055572986602783, -0.15163522958755493, -0.07008028775453568], [-0.8386706709861755, 0.02466297149658203, -0.8386706709861755, -0.060653284192085266, -0.029407218098640442], [0.0, -0.019131334498524666, -1.883415937423706, 0.020113304257392883, 0.010157785378396511], [-1.3343093395233154, 0.37013623118400574, -1.3343093395233154, -1.181653618812561, -0.27739912271499634], [0.0, -0.11689889430999756, -0.746537983417511, 0.2754718065261841, 0.15658800303936005], [-0.918312132358551, 0.0671892985701561, -0.918312132358551, -0.15893596410751343, -0.07316607981920242], [-0.9745298624038696, 0.11767285317182541, -0.9745298624038696, -0.2806117832660675, -0.12074832618236542], [-1.3212873935699463, 0.3573783040046692, -1.3212873935699463, -1.0222632884979248, -0.2704773545265198], [-1.642871618270874, 0.4451664090156555, -1.642871618270874, -1.5584088563919067, -0.2709684669971466], [-0.9464289546012878, 0.18794980645179749, -0.9464289546012878, -0.539040744304657, -0.19858840107917786], [-1.5319135189056396, 0.4217758774757385, -1.5319135189056396, -1.1147007942199707, -0.2753261625766754], [-1.2840321063995361, 0.3546903729438782, -1.2840321063995361, -1.4265795946121216, -0.27623170614242554], [0.0, -0.13221783936023712, -0.5954167246818542, 0.3747209310531616, 0.22205932438373566], [0.0, -0.0603618249297142, -0.7442622184753418, 0.15084953606128693, 0.0811029002070427], [0.0, -0.15920400619506836, -1.0279167890548706, 0.27278393507003784, 0.15488024055957794], [-1.5798078775405884, 0.42062830924987793, -1.5798078775405884, -0.965364933013916, -0.2662528157234192], [-1.0918631553649902, 0.2840961217880249, -1.0918631553649902, -0.900465726852417, -0.2601938843727112], [-1.4193172454833984, 0.07080616056919098, -1.4193172454833984, -0.10531552135944366, -0.049887482076883316], [-0.665798008441925, 0.13929109275341034, -0.665798008441925, -0.5845804214477539, -0.20920923352241516], [-1.0383473634719849, 0.2651347815990448, -1.0383473634719849, -0.8568800091743469, -0.2553430497646332], [-0.6244423389434814, 0.14403432607650757, -0.6244423389434814, -0.6909865140914917, -0.23066073656082153], [-1.4965132474899292, 0.3560791313648224, -1.4965132474899292, -0.7333282232284546, -0.23793917894363403], [-0.8868429660797119, 0.21197257936000824, -0.8868429660797119, -0.7399765253067017, -0.23901928961277008], [-1.5937116146087646, 0.17118053138256073, -1.5937116146087646, -0.2445819079875946, -0.10740998387336731], [-1.3679810762405396, 0.3689359724521637, -1.3679810762405396, -1.5830669403076172, -0.2696937620639801], [0.0, -0.18727868795394897, -0.9137213230133057, 0.34947338700294495, 0.2049625962972641], [0.0, -0.09695199877023697, -0.9842748641967773, 0.180716872215271, 0.09850093722343445], [-1.4592198133468628, 0.31289851665496826, -1.4592198133468628, -2.2510902881622314, -0.2144286334514618], [-1.2082492113113403, 0.25198042392730713, -1.2082492113113403, -0.5816397070884705, -0.20855003595352173], [-1.172025442123413, 0.31831833720207214, -1.172025442123413, -1.0400128364562988, -0.2715967893600464], [-1.0256637334823608, 0.2676188051700592, -1.0256637334823608, -0.9075559377670288, -0.26092255115509033], [-0.9715796709060669, 0.2213415652513504, -0.9715796709060669, -0.6754608750343323, -0.22781617939472198], [-1.6622655391693115, 0.44395437836647034, -1.6622655391693115, -0.9755005836486816, -0.26707789301872253], [-1.9854984283447266, 0.5303447842597961, -1.9854984283447266, -0.9758926033973694, -0.2671091556549072], [-1.2952284812927246, 0.3182424008846283, -1.2952284812927246, -0.78367018699646, -0.24570366740226746], [-1.2814605236053467, 0.19792871177196503, -1.2814605236053467, -0.38040512800216675, -0.15445557236671448], [-1.0704693794250488, 0.15440064668655396, -1.0704693794250488, -0.34863927960395813, -0.14423640072345734], [-0.6890120506286621, 0.046853985637426376, -0.6890120506286621, -0.14675220847129822, -0.06800169497728348], [-1.508743166923523, 0.02531205117702484, -1.508743166923523, -0.034136414527893066, -0.016776911914348602], [-1.0729137659072876, 0.07014744728803635, -1.0729137659072876, -0.140633225440979, -0.06538031995296478], [-0.6684796810150146, 0.06824514269828796, -0.6684796810150146, -0.23066630959510803, -0.10209008306264877], [-1.7638643980026245, 0.35611528158187866, -1.7638643980026245, -0.552817165851593, -0.20189493894577026], [-0.9013867378234863, 0.1527697890996933, -0.9013867378234863, -0.43003004789352417, -0.16948306560516357], [0.0, -0.727200448513031, -1.3885984420776367, 0.7669191360473633, 0.523693859577179], [0.0, -0.1155913695693016, -1.322906494140625, 0.16170743107795715, 0.08737682551145554], [-1.4614980220794678, 0.3233092725276947, -1.4614980220794678, -0.6412976980209351, -0.22121773660182953], [-1.4423296451568604, 0.30708548426628113, -1.4423296451568604, -0.6013984680175781, -0.21290937066078186], [-1.350550651550293, 0.352927029132843, -1.350550651550293, -1.7185286283493042, -0.2613208293914795], [0.0, -0.2417285293340683, -0.8636853694915771, 0.4570807218551636, 0.2798803150653839], [0.0, -0.02141137421131134, -0.8121656775474548, 0.051405638456344604, 0.0263633094727993], [-1.6076418161392212, 0.3648682236671448, -1.6076418161392212, -2.1224827766418457, -0.22695866227149963], [-1.060484528541565, 0.19564266502857208, -1.060484528541565, -2.552056312561035, -0.18448422849178314], [-0.8980315923690796, 0.24541179835796356, -0.8980315923690796, -1.0699260234832764, -0.2732774615287781], [-0.5066250562667847, 0.04510379210114479, -0.5066250562667847, -0.19749487936496735, -0.08902795612812042], [-0.4175263047218323, 0.058933574706315994, -0.4175263047218323, -0.3393225371837616, -0.1411493718624115], [-1.2068233489990234, 0.13449370861053467, -1.2068233489990234, -0.25530266761779785, -0.11144440621137619], [0.0, -0.20918163657188416, -0.5518171787261963, 0.5893480181694031, 0.3790777921676636], [-1.5561290979385376, 0.35056769847869873, -1.5561290979385376, -0.6620500087738037, -0.22528189420700073], [-1.4353762865066528, 0.3758188784122467, -1.4353762865066528, -0.9165814518928528, -0.2618260383605957], [-1.6135649681091309, 0.1932016909122467, -1.6135649681091309, -0.2778165638446808, -0.11973591893911362], [-0.6596132516860962, 0.14297564327716827, -0.6596132516860962, -0.6194843053817749, -0.21675677597522736], [-1.677789330482483, 0.4052382707595825, -1.677789330482483, -0.7558548450469971, -0.24153107404708862], [-1.3747215270996094, 0.37621259689331055, -1.3747215270996094, -1.4993622303009033, -0.27366459369659424], [-1.4871742725372314, 0.38054847717285156, -1.4871742725372314, -0.8614913821220398, -0.2558869421482086], [-1.1615468263626099, 0.07785787433385849, -1.1615468263626099, -0.1444777548313141, -0.06702947616577148], [-0.8289705514907837, 0.09363538771867752, -0.8289705514907837, -0.2593521475791931, -0.11295381933450699], [0.0, -0.12960028648376465, -0.6720722913742065, 0.33129268884658813, 0.19283682107925415], [0.0, -0.014306114986538887, -1.023869276046753, 0.027565300464630127, 0.013972599059343338], [0.0, -1.6196836233139038, -1.369137167930603, 1.4582200050354004, 1.1829959154129028], [0.0, -0.6626669764518738, -1.2191317081451416, 0.7901979684829712, 0.5435565114021301], [-0.9583929181098938, 0.08364040404558182, -0.9583929181098938, -0.193136066198349, -0.08727151900529861], [-1.1589446067810059, 0.18982186913490295, -1.1589446067810059, -0.4107809066772461, -0.1637885570526123], [-1.148627758026123, 0.2892293930053711, -1.148627758026123, -1.844583511352539, -0.25180429220199585], [-0.7534003257751465, 0.09636685252189636, -0.7534003257751465, -0.30068737268447876, -0.12790922820568085], [0.0, -0.18772655725479126, -0.9819154143333435, 0.3287963271141052, 0.19118404388427734], [0.0, -0.22281908988952637, -1.3227530717849731, 0.29399430751800537, 0.16845101118087769], [-1.60386061668396, 0.39153897762298584, -1.60386061668396, -1.9358104467391968, -0.24412281811237335], [-0.8566415309906006, 0.1451566219329834, -0.8566415309906006, -0.42991137504577637, -0.16944849491119385], [-1.2200511693954468, 0.25374287366867065, -1.2200511693954468, -0.5790974497795105, -0.20797723531723022], [-0.9899402856826782, 0.1537678986787796, -0.9899402856826782, -0.38319462537765503, -0.15533047914505005], [-1.4679582118988037, 0.40640342235565186, -1.4679582118988037, -1.4037706851959229, -0.2768494486808777], [-1.5159454345703125, 0.3760250210762024, -1.5159454345703125, -1.8900654315948486, -0.24804653227329254], [0.0, -0.0466679222881794, -1.0716426372528076, 0.08360332250595093, 0.04354802519083023], [-1.2086800336837769, 0.33537232875823975, -1.2086800336837769, -1.3761765956878662, -0.2774699032306671], [-1.331148386001587, 0.37012699246406555, -1.331148386001587, -1.2176625728607178, -0.27805089950561523], [-1.3538259267807007, 0.36700236797332764, -1.3538259267807007, -1.031721591949463, -0.27108535170555115], [-0.9796366095542908, 0.25369903445243835, -0.9796366095542908, -0.8889300227165222, -0.2589725852012634], [-1.0745909214019775, 0.27130991220474243, -1.0745909214019775, -0.8335442543029785, -0.25247737765312195], [-1.3714393377304077, 0.351727157831192, -1.3714393377304077, -0.8664683103561401, -0.25646570324897766], [-0.43959808349609375, 0.09043082594871521, -0.43959808349609375, -0.5691627264022827, -0.20571251213550568], [0.0, -0.01069749053567648, -1.053266167640686, 0.02011077105998993, 0.010156492702662945], [-1.2432512044906616, 0.2865912914276123, -1.2432512044906616, -0.6901928186416626, -0.23051761090755463], [-0.8861912488937378, 0.1868220716714859, -0.8861912488937378, -0.5918111801147461, -0.21081462502479553], [-1.3498361110687256, 0.2927424907684326, -1.3498361110687256, -0.6200389266014099, -0.21687261760234833], [-1.1043825149536133, 0.3059324324131012, -1.1043825149536133, -1.3969178199768066, -0.2770167291164398], [-0.8760045170783997, 0.2175423949956894, -0.8760045170783997, -0.8022699952125549, -0.24833479523658752], [-0.5329040288925171, 0.05510910972952843, -0.5329040288925171, -0.23410336673259735, -0.10341282188892365], [-0.8182849884033203, 0.08019948750734329, -0.8182849884033203, -0.22015522420406342, -0.09800923615694046], [-0.8482248783111572, 0.09116395562887192, -0.8482248783111572, -0.2447565793991089, -0.10747615993022919], [0.0, -0.036790259182453156, -0.40542954206466675, 0.16749347746372223, 0.09074389934539795], [-1.5072617530822754, 0.2865738570690155, -1.5072617530822754, -0.5052474141120911, -0.19012878835201263], [-1.2153109312057495, 0.3380356729030609, -1.2153109312057495, -1.3330917358398438, -0.27814748883247375], [-1.0407392978668213, 0.0579240620136261, -1.0407392978668213, -0.11830294132232666, -0.05565664917230606], [-1.618721842765808, 0.4495745301246643, -1.618721842765808, -1.1980276107788086, -0.27773427963256836], [-1.2402524948120117, 0.3438722789287567, -1.2402524948120117, -1.3862483501434326, -0.277259886264801], [-1.1989630460739136, 0.25666844844818115, -1.1989630460739136, -0.6068125367164612, -0.21407535672187805], [-1.242195963859558, 0.22831274569034576, -1.242195963859558, -0.48117882013320923, -0.183797687292099], [-1.1283848285675049, 0.15605634450912476, -1.1283848285675049, -0.33083269000053406, -0.13830064237117767], [0.0, -0.051804911345243454, -0.1020176112651825, 0.7481235861778259, 0.5078036189079285], [-1.3933005332946777, 0.24813242256641388, -1.3933005332946777, -0.46027427911758423, -0.1780896633863449], [-1.312391996383667, 0.3628081977367401, -1.312391996383667, -1.418973684310913, -0.2764480412006378], [-0.9999372363090515, 0.2584799528121948, -0.9999372363090515, -0.8845407962799072, -0.25849616527557373], [0.0, -0.17880664765834808, -0.9725731611251831, 0.31766319274902344, 0.1838490515947342], [-0.8657717704772949, 0.05310577526688576, -0.8657717704772949, -0.13128381967544556, -0.061339233070611954], [-1.4937894344329834, 0.18202245235443115, -1.4937894344329834, -0.2836732268333435, -0.1218528226017952], [-1.7459819316864014, 0.47710269689559937, -1.7459819316864014, -1.5090662240982056, -0.2732575237751007], [-1.058638334274292, 0.2786857485771179, -1.058638334274292, -0.9313750267028809, -0.2632492482662201], [-1.673614263534546, 0.39804941415786743, -1.673614263534546, -2.006241798400879, -0.23783820867538452], [-1.4694314002990723, 0.22209259867668152, -1.4694314002990723, -2.901134490966797, -0.15114186704158783], [-0.7712554335594177, 0.16711968183517456, -0.7712554335594177, -0.6191421747207642, -0.2166852504014969], [-1.2003644704818726, 0.1799086034297943, -1.2003644704818726, -0.3659951090812683, -0.14987830817699432], [-1.7350983619689941, 0.47258269786834717, -1.7350983619689941, -1.0531529188156128, -0.2723665237426758], [-1.5881085395812988, 0.29234299063682556, -1.5881085395812988, -2.5561208724975586, -0.1840825080871582], [-0.8562499284744263, 0.14657963812351227, -0.8562499284744263, -0.43590685725212097, -0.17118790745735168], [0.0, -0.24011088907718658, -1.0973939895629883, 0.36994296312332153, 0.21880099177360535], [-1.2216609716415405, 0.31521332263946533, -1.2216609716415405, -0.8802151083946228, -0.258020281791687], [-0.5004863739013672, 0.003901973832398653, -0.5004863739013672, -0.015716224908828735, -0.007796363905072212], [-1.8556032180786133, 0.3213801681995392, -1.8556032180786133, -0.4428941309452057, -0.17319443821907043], [-1.5529139041900635, 0.4022899568080902, -1.5529139041900635, -1.7503806352615356, -0.25905489921569824], [-1.3583327531814575, 0.1810837835073471, -1.3583327531814575, -3.103768825531006, -0.13331326842308044], [-0.9902945756912231, 0.13145481050014496, -0.9902945756912231, -0.3145546615123749, -0.13274313509464264], [-1.1693675518035889, 0.24899190664291382, -1.1693675518035889, -0.6014877557754517, -0.21292869746685028], [-1.411700963973999, 0.14549992978572845, -1.411700963973999, -0.23320360481739044, -0.10306710749864578], [-0.8947659730911255, 0.1765996664762497, -0.8947659730911255, -0.5340472459793091, -0.19736966490745544], [-1.3054279088974, 0.27006492018699646, -1.3054279088974, -0.57425457239151, -0.20687846839427948], [-1.1793721914291382, 0.26811927556991577, -1.1793721914291382, -0.6729154586791992, -0.2273406833410263], [-1.9824378490447998, 0.311095267534256, -1.9824378490447998, -0.38831043243408203, -0.15692560374736786], [-1.317299246788025, 0.3646981120109558, -1.317299246788025, -1.4036343097686768, -0.27685290575027466], [-1.833663821220398, 0.05617854371666908, -1.833663821220398, -0.06327588856220245, -0.030637318268418312], [-1.1821939945220947, 0.32348617911338806, -1.1821939945220947, -1.0768835544586182, -0.2736320495605469], [-1.6469303369522095, 0.41067057847976685, -1.6469303369522095, -0.809732973575592, -0.24935515224933624], [-1.5515258312225342, 0.3638197183609009, -1.5515258312225342, -0.7127668261528015, -0.23449157178401947], [-1.0522338151931763, 0.16529913246631622, -1.0522338151931763, -0.3888513445854187, -0.15709353983402252], [-1.7173657417297363, 0.3338056802749634, -1.7173657417297363, -0.521943986415863, -0.19437076151371002], [0.0, -0.05252945050597191, -1.8560532331466675, 0.05508650839328766, 0.028301693499088287], [-1.1964092254638672, 0.3326886296272278, -1.1964092254638672, -1.3392865657806396, -0.2780725955963135], [-1.33180832862854, 0.3667868673801422, -1.33180832862854, -1.452907919883728, -0.2754051387310028], [-1.2427188158035278, 0.31731054186820984, -1.2427188158035278, -0.8568185567855835, -0.2553357481956482], [-0.8133280277252197, 0.19582423567771912, -0.8133280277252197, -0.7509738206863403, -0.24076907336711884], [-1.637062907218933, 0.3335702121257782, -1.637062907218933, -2.3584535121917725, -0.20376138389110565], [-1.0494000911712646, 0.22614426910877228, -1.0494000911712646, -2.2402455806732178, -0.21549861133098602], [-1.0530719757080078, 0.08612237125635147, -1.0530719757080078, -0.17965957522392273, -0.0817820355296135], [-1.824160099029541, 0.2426266372203827, -1.824160099029541, -0.3153201937675476, -0.13300731778144836], [-0.8467833995819092, 0.22866632044315338, -0.8467833995819092, -1.0157172679901123, -0.2700411081314087], [-0.8805421590805054, 0.04857369884848595, -0.8805421590805054, -0.11718513071537018, -0.05516339838504791], [0.0, -0.1798335760831833, -1.3757261037826538, 0.23414960503578186, 0.13071902096271515], [-1.787400722503662, 0.48601198196411133, -1.787400722503662, -1.5390352010726929, -0.2719099223613739], [-1.0276814699172974, 0.1394793540239334, -1.0276814699172974, -0.3232349753379822, -0.135722354054451], [-1.1996467113494873, 0.3336523771286011, -1.1996467113494873, -1.3349767923355103, -0.278125524520874], [0.0, -0.1160535141825676, -1.2789310216903687, 0.16749122738838196, 0.09074258804321289], [-1.1762051582336426, 0.11686844378709793, -1.1762051582336426, -0.22362060844898224, -0.09936059266328812], [-2.110383987426758, 0.5637218356132507, -2.110383987426758, -1.6287434101104736, -0.2671181261539459], [-1.1208305358886719, 0.18089742958545685, -1.1208305358886719, -2.7905616760253906, -0.1613958775997162], [-1.1798443794250488, 0.27533185482025146, -1.1798443794250488, -0.7062390446662903, -0.23336286842823029], [-0.86548912525177, 0.1256568282842636, -0.86548912525177, -0.3515300154685974, -0.1451859176158905], [-1.9635848999023438, 0.44037386775016785, -1.9635848999023438, -0.6568011045455933, -0.22427034378051758], [-1.2394278049468994, 0.2937178313732147, -1.2394278049468994, -2.015655279159546, -0.23697856068611145], [-1.2320127487182617, 0.3337099552154541, -1.2320127487182617, -1.028256893157959, -0.27086567878723145], [-1.5764033794403076, 0.4322720766067505, -1.5764033794403076, -1.0889290571212769, -0.27421411871910095], [-0.6546456217765808, 0.12228533625602722, -0.6546456217765808, -0.4924567937850952, -0.18679623305797577], [-1.3027229309082031, 0.30270275473594666, -1.3027229309082031, -0.7005269527435303, -0.2323615700006485], [-1.9647841453552246, 0.5335808992385864, -1.9647841453552246, -1.0396077632904053, -0.2715722620487213], [-1.3359651565551758, 0.3682737946510315, -1.3359651565551758, -1.4451444149017334, -0.2756612300872803], [-1.0700500011444092, 0.2915928363800049, -1.0700500011444092, -1.5261906385421753, -0.27250394225120544], [-1.2217895984649658, 0.3204180896282196, -1.2217895984649658, -0.9209432601928711, -0.262253075838089], [0.0, -1.0403553247451782, -1.7344355583190918, 0.8549349904060364, 0.599823534488678], [0.0, -0.3824140429496765, -1.7831101417541504, 0.3635598123073578, 0.21446461975574493], [-1.6573017835617065, 0.25629740953445435, -1.6573017835617065, -0.38101571798324585, -0.15464739501476288], [0.0, -0.022435834631323814, -1.4950941801071167, 0.02957528829574585, 0.015006301924586296], [-1.5211265087127686, 0.3365621268749237, -1.5211265087127686, -0.6415014863014221, -0.2212584763765335], [-1.5245929956436157, 0.3463459014892578, -1.5245929956436157, -2.120246648788452, -0.22717270255088806], [-1.4034934043884277, 0.25564199686050415, -1.4034934043884277, -2.575735330581665, -0.18214692175388336], [-1.0638694763183594, 0.15831954777240753, -1.0638694763183594, -2.9267663955688477, -0.1488148272037506], [-0.7631862163543701, 0.14814884960651398, -0.7631862163543701, -0.5209388732910156, -0.19411887228488922], [-1.0340092182159424, 0.03636760637164116, -1.0340092182159424, -0.07300671935081482, -0.03517145290970802], [-1.6413066387176514, 0.2797667980194092, -1.6413066387176514, -0.43336930871009827, -0.17045371234416962], [-0.8632117509841919, 0.19241425395011902, -0.8632117509841919, -0.6498059034347534, -0.22290503978729248], [-0.9690194725990295, 0.13760316371917725, -0.9690194725990295, -0.341884970664978, -0.14200247824192047], [-1.818204641342163, 0.4730674624443054, -1.818204641342163, -0.9003689289093018, -0.26018384099006653], [-1.4636951684951782, 0.3411506414413452, -1.4636951684951782, -0.7045890688896179, -0.23307493329048157], [-1.5111358165740967, 0.09449125081300735, -1.5111358165740967, -0.13402825593948364, -0.06252995133399963], [-1.7030251026153564, 0.10533496737480164, -1.7030251026153564, -0.13246390223503113, -0.061851684004068375], [-1.5798757076263428, 0.15933026373386383, -1.5798757076263428, -0.2274571806192398, -0.10084987431764603], [-1.6696311235427856, 0.44124650955200195, -1.6696311235427856, -0.9425549507141113, -0.264277845621109], [-1.3695075511932373, 0.3670106828212738, -1.3695075511932373, -0.987155556678772, -0.26798734068870544], [-1.163111925125122, 0.3051571249961853, -1.163111925125122, -0.9220727682113647, -0.26236265897750854], [-1.7861104011535645, 0.3813450336456299, -1.7861104011535645, -2.2604284286499023, -0.21350586414337158], [-1.7021803855895996, 0.45072469115257263, -1.7021803855895996, -1.6664988994598389, -0.2647925615310669], [0.0, -0.001475239754654467, -1.1394143104553223, 0.0025861263275146484, 0.0012947351206094027], [0.0, -1.1892684698104858, -1.8107585906982422, 0.9188257455825806, 0.6567791700363159], [0.0, -0.4181284010410309, -1.4325127601623535, 0.47364872694015503, 0.2918846011161804], [-1.2526180744171143, 0.3297716975212097, -1.2526180744171143, -0.9315530061721802, -0.2632659673690796], [-1.2170788049697876, 0.1945236772298813, -1.2170788049697876, -2.8072357177734375, -0.1598283350467682], [-0.6569619178771973, 0.068876251578331, -0.6569619178771973, -0.23783013224601746, -0.10484055429697037], [-1.8074554204940796, 0.031331244856119156, -1.8074554204940796, -0.035291582345962524, -0.017334450036287308], [-1.0742279291152954, 0.24810761213302612, -1.0742279291152954, -0.6926712393760681, -0.23096366226673126], [-1.2078075408935547, 0.19515450298786163, -1.2078075408935547, -0.4034576117992401, -0.1615774780511856], [-1.497007131576538, 0.30125898122787476, -1.497007131576538, -0.5500648021697998, -0.20124085247516632], [-1.3874664306640625, 0.386332631111145, -1.3874664306640625, -1.2650010585784912, -0.27844467759132385], [-0.8695435523986816, 0.2100909799337387, -0.8695435523986816, -0.7563679218292236, -0.24161064624786377], [-1.3135757446289062, 0.3457299470901489, -1.3135757446289062, -0.9308246374130249, -0.26319757103919983], [0.0, -0.46771618723869324, -1.8297451734542847, 0.4230584502220154, 0.25561821460723877], [-1.371576189994812, 0.3346109092235565, -1.371576189994812, -1.9376658201217651, -0.24396087229251862], [-0.9937635660171509, 0.09791950136423111, -0.9937635660171509, -0.22149914503097534, -0.0985340029001236], [0.0, -0.04276202991604805, -0.7449472546577454, 0.1088835597038269, 0.05740276351571083], [-2.0021743774414062, 0.3133802115917206, -2.0021743774414062, -0.38700568675994873, -0.15651993453502655], [-0.9939686059951782, 0.12052667140960693, -0.9939686059951782, -0.28202301263809204, -0.12125802785158157], [0.0, -0.3528502285480499, -1.0993471145629883, 0.5131033658981323, 0.32096344232559204], [-0.6828578114509583, 0.06676080822944641, -0.6828578114509583, -0.21953508257865906, -0.09776677936315536], [0.0, -0.10529470443725586, -1.0426636934280396, 0.18492284417152405, 0.10098625719547272], [0.0, -0.24100209772586823, -1.9168144464492798, 0.2260255068540573, 0.12573052942752838], [-1.7201582193374634, 0.39745014905929565, -1.7201582193374634, -2.0793848037719727, -0.2310544103384018], [-1.343312382698059, 0.3486900329589844, -1.343312382698059, -1.7431966066360474, -0.2595748007297516], [-1.0329755544662476, 0.21962478756904602, -1.0329755544662476, -0.6000345945358276, -0.21261373162269592], [-1.582648754119873, 0.3575840890407562, -1.582648754119873, -0.6654976606369019, -0.2259402722120285], [0.0, -1.5064659118652344, -1.6312847137451172, 1.2012773752212524, 0.9234843254089355], [-1.556363821029663, 0.4145517945289612, -1.556363821029663, -0.9666498303413391, -0.2663591802120209], [0.0, -1.469027042388916, -1.6252989768981934, 1.1812400817871094, 0.9038503170013428], [-1.6618727445602417, 0.2410144805908203, -1.6618727445602417, -0.35104185342788696, -0.145025834441185], [-1.0947363376617432, 0.20910029113292694, -1.0947363376617432, -0.508657693862915, -0.1910051554441452], [-1.5966274738311768, 0.4249424934387207, -1.5966274738311768, -1.6447991132736206, -0.2661500573158264], [-1.2845041751861572, 0.3397834002971649, -1.2845041751861572, -1.6706761121749878, -0.2645249366760254], [-0.7361642122268677, 0.14158961176872253, -0.7361642122268677, -0.5138682126998901, -0.19233427941799164], [-0.7111445069313049, 0.11027337610721588, -0.7111445069313049, -0.38234591484069824, -0.155064657330513], [-0.8928295373916626, 0.2485969066619873, -0.8928295373916626, -1.294377326965332, -0.27843713760375977], [-1.2506115436553955, 0.26704809069633484, -1.2506115436553955, -2.260143756866455, -0.21353401243686676], [-0.8996356129646301, 0.19565349817276, -0.8996356129646301, -0.6229607462882996, -0.2174808233976364], [-1.0215680599212646, 0.2497948855161667, -1.0215680599212646, -0.7755895256996155, -0.24452103674411774], [-1.75481116771698, 0.1944504827260971, -1.75481116771698, -0.25360679626464844, -0.11080992221832275], [0.0, -0.18286845088005066, -1.9833394289016724, 0.16999083757400513, 0.09220229834318161], [-1.6295320987701416, 0.3725401759147644, -1.6295320987701416, -2.105104684829712, -0.22861787676811218], [-1.1132545471191406, 0.12008057534694672, -1.1132545471191406, -0.24578219652175903, -0.10786443948745728], [-1.0036660432815552, 0.2366897612810135, -1.0036660432815552, -0.7206060290336609, -0.23582521080970764], [-0.986585259437561, 0.18917757272720337, -0.986585259437561, -0.5115712881088257, -0.19174984097480774], [-1.4973905086517334, 0.2501668334007263, -1.4973905086517334, -0.42179805040359497, -0.16706854104995728], [-1.521446943283081, 0.29106393456459045, -1.521446943283081, -0.5098381042480469, -0.19130732119083405], [-1.4451806545257568, 0.3277897238731384, -1.4451806545257568, -2.1239748001098633, -0.22681574523448944], [-1.6709413528442383, 0.35184746980667114, -1.6709413528442383, -2.2900755405426025, -0.2105684131383896], [-0.7983652353286743, 0.12488650530576706, -0.7983652353286743, -0.38670969009399414, -0.1564277857542038], [-1.688672661781311, 0.3855457603931427, -1.688672661781311, -0.6781349778175354, -0.2283129096031189], [-1.1220438480377197, 0.2790810763835907, -1.1220438480377197, -0.805111289024353, -0.24872563779354095], [-1.7610547542572021, 0.027381740510463715, -1.7610547542572021, -0.031596094369888306, -0.015548489056527615], [-1.7981196641921997, 0.153114452958107, -1.7981196641921997, -0.18790802359580994, -0.0851525366306305], [-1.1798056364059448, 0.058785732835531235, -1.1798056364059448, -0.10517951846122742, -0.04982662573456764], [-1.295375943183899, 0.25820955634117126, -1.295375943183899, -0.5421082973480225, -0.19933176040649414], [-1.721532940864563, 0.41099801659584045, -1.721532940864563, -0.7382447719573975, -0.23873956501483917], [-1.5789767503738403, 0.43820205330848694, -1.5789767503738403, -1.1873351335525513, -0.2775228023529053], [-1.2360087633132935, 0.3252049684524536, -1.2360087633132935, -0.9298827648162842, -0.2631089389324188], [-1.4618598222732544, 0.15544447302818298, -1.4618598222732544, -0.24174576997756958, -0.10633336752653122], [0.0, -1.1634823083877563, -1.5862090587615967, 1.002629280090332, 0.733498752117157], [-0.922256350517273, 0.16230528056621552, -0.922256350517273, -0.4527501165866852, -0.17598716914653778], [-1.498485803604126, 0.36740773916244507, -1.498485803604126, -0.7801127433776855, -0.2451860010623932], [-1.4242405891418457, 0.3475116193294525, -1.4242405891418457, -0.7720659971237183, -0.24399784207344055], [-1.704770803451538, 0.4741559326648712, -1.704770803451538, -1.3341959714889526, -0.27813470363616943], [-1.587902307510376, 0.3047427535057068, -1.587902307510376, -2.4771852493286133, -0.19191530346870422], [-1.0913976430892944, 0.11644168198108673, -1.0913976430892944, -0.2426852285861969, -0.1066904291510582], [0.0, -0.3230343461036682, -1.1150596141815186, 0.4706481099128723, 0.2897014021873474], [0.0, -0.5740677118301392, -0.8381316065788269, 0.9498662948608398, 0.6849374175071716], [0.0, -1.7053844928741455, -1.525200605392456, 1.3951952457427979, 1.1181378364562988], [-1.716897964477539, 0.46694326400756836, -1.716897964477539, -1.046263337135315, -0.27196913957595825], [-1.357969045639038, 0.33817240595817566, -1.357969045639038, -1.8783591985702515, -0.2490280717611313], [-1.652620553970337, 0.3146052360534668, -1.652620553970337, -2.4927382469177246, -0.19036749005317688], [-1.6070072650909424, 0.28663313388824463, -1.6070072650909424, -2.6142263412475586, -0.178364560008049], [-1.0869522094726562, 0.29205089807510376, -1.0869522094726562, -0.9965200424194336, -0.268687903881073], [-1.3706194162368774, 0.2315646857023239, -1.3706194162368774, -0.428199827671051, -0.1689489334821701], [-1.073035717010498, 0.29879888892173767, -1.073035717010498, -1.2729734182357788, -0.2784612774848938], [-1.7425075769424438, 0.27213385701179504, -1.7425075769424438, -0.38589417934417725, -0.1561737060546875], [-2.043872594833374, 0.26375487446784973, -2.043872594833374, -0.3039267361164093, -0.12904663383960724], [-1.4770668745040894, 0.34998762607574463, -1.4770668745040894, -2.0159921646118164, -0.23694771528244019], [-1.6905262470245361, 0.4706600606441498, -1.6905262470245361, -1.3008840084075928, -0.2784103751182556], [-1.5835158824920654, 0.17144054174423218, -1.5835158824920654, -0.24684365093708038, -0.10826575756072998], [0.0, -0.352861225605011, -1.863391637802124, 0.3260437250137329, 0.18936502933502197], [-1.7708501815795898, 0.48900306224823, -1.7708501815795898, -1.4296917915344238, -0.2761402726173401], [-1.8842588663101196, 0.25207027792930603, -1.8842588663101196, -3.098297119140625, -0.13377688825130463], [-1.0162652730941772, 0.23237748444080353, -1.0162652730941772, -2.104680061340332, -0.2286582887172699], [-1.4611353874206543, 0.4022124707698822, -1.4611353874206543, -1.1133911609649658, -0.2752739191055298], [-0.6886727809906006, 0.19030463695526123, -0.6886727809906006, -1.1427600383758545, -0.27633535861968994], [-1.3275715112686157, 0.35843369364738464, -1.3275715112686157, -1.0149922370910645, -0.26999199390411377], [-1.1220998764038086, 0.3071082532405853, -1.1220998764038086, -1.0780600309371948, -0.27369067072868347], [-1.6561732292175293, 0.34422242641448975, -1.6561732292175293, -0.5784991979598999, -0.20784203708171844], [-1.7392709255218506, 0.3474479019641876, -1.7392709255218506, -2.3984782695770264, -0.19976641237735748], [-1.3534983396530151, 0.35896435379981995, -1.3534983396530151, -1.6598834991455078, -0.2652122676372528], [0.0, -0.021715223789215088, -0.6855982542037964, 0.06145879626274109, 0.03167339414358139], [-1.7568490505218506, 0.4306409955024719, -1.7568490505218506, -0.7796698212623596, -0.24512122571468353], [-1.6253256797790527, 0.44210392236709595, -1.6253256797790527, -1.0469512939453125, -0.2720094323158264], [-1.2723984718322754, 0.07576017826795578, -1.2723984718322754, -0.12715590000152588, -0.059541236609220505], [-1.4750850200653076, 0.39450350403785706, -1.4750850200653076, -0.9801355600357056, -0.26744458079338074], [-0.9024868607521057, 0.20258298516273499, -0.9024868607521057, -0.6578426361083984, -0.22447195649147034], [-1.2959738969802856, 0.10248778760433197, -1.2959738969802856, -0.1731095016002655, -0.07908167690038681], [0.0, -1.8546645641326904, -1.8208529949188232, 1.2969965934753418, 1.0185691118240356], [0.0, -0.9691126942634583, -1.0879156589508057, 1.167863130569458, 0.8907976150512695], [0.0, -9.499062538146973, -2.0365195274353027, 4.706509590148926, 4.664361000061035], [0.0, -4.1424479484558105, -1.5406622886657715, 2.845046043395996, 2.6887450218200684], [0.0, -2.0217063426971436, -1.3975529670715332, 1.7086095809936523, 1.4466043710708618], [-1.8238197565078735, 0.4689607322216034, -1.8238197565078735, -1.7763957977294922, -0.25713106989860535], [-0.865182101726532, 0.15888243913650513, -0.865182101726532, -0.4805932641029358, -0.1836404651403427], [-1.2980830669403076, 0.04103744029998779, -1.2980830669403076, -0.06536316871643066, -0.03161387890577316], [-2.1268534660339355, 0.4471628665924072, -2.1268534660339355, -0.5892396569252014, -0.21024620532989502], [-1.919304370880127, 0.48366692662239075, -1.919304370880127, -1.8421475887298584, -0.25200116634368896], [-1.359717845916748, 0.3626404106616974, -1.359717845916748, -1.635697841644287, -0.26670268177986145], [-1.2674660682678223, 0.326984703540802, -1.2674660682678223, -0.8798786997795105, -0.25798299908638], [0.0, -0.29507946968078613, -1.7401840686798096, 0.29572513699531555, 0.16956795752048492], [-1.1016249656677246, 0.20250998437404633, -1.1016249656677246, -0.48129335045814514, -0.1838284283876419], [-0.7215489149093628, 0.14431415498256683, -0.7215489149093628, -0.5449056029319763, -0.20000605285167694], [-0.5947971343994141, 0.1040891706943512, -0.5947971343994141, -0.44924646615982056, -0.1749994456768036], [-0.9675015807151794, 0.013607347384095192, -0.9675015807151794, -0.028535962104797363, -0.014064419083297253], [0.0, -0.7188929319381714, -1.926429271697998, 0.5817482471466064, 0.3731738030910492], [-1.9045348167419434, 0.4117654860019684, -1.9045348167419434, -2.2330989837646484, -0.21620266139507294], [-1.8251768350601196, 0.4922727048397064, -1.8251768350601196, -1.0109063386917114, -0.26971232891082764], [-1.0625262260437012, 0.29448840022087097, -1.0625262260437012, -1.1715251207351685, -0.2771587073802948], [-0.8280337452888489, 0.14517763257026672, -0.8280337452888489, -0.45041030645370483, -0.17532816529273987], [-2.022839307785034, 0.2847253680229187, -2.022839307785034, -0.3381420969963074, -0.1407553106546402], [-1.656512975692749, 0.2521945834159851, -1.656512975692749, -2.889066696166992, -0.15224425494670868], [-1.2971205711364746, 0.3379702866077423, -1.2971205711364746, -1.7294658422470093, -0.2605542540550232], [0.0, -4.344379425048828, -1.671626091003418, 2.7629055976867676, 2.5988943576812744], [-1.6520277261734009, 0.4479614496231079, -1.6520277261734009, -1.0328888893127441, -0.2711585462093353], [-1.6023333072662354, 0.4451645612716675, -1.6023333072662354, -1.3566060066223145, -0.27782270312309265], [-1.955573320388794, 0.5079818964004517, -1.955573320388794, -0.8963295221328735, -0.25976109504699707], [-1.3972597122192383, 0.3373177647590637, -1.3972597122192383, -0.7550997734069824, -0.24141378700733185], [-1.0425829887390137, 0.2168814092874527, -1.0425829887390137, -0.5793008804321289, -0.20802316069602966], [-1.7175602912902832, 0.45967891812324524, -1.7175602912902832, -0.9825736284255981, -0.2676348090171814], [-1.783231258392334, 0.45641055703163147, -1.783231258392334, -1.7920184135437012, -0.2559458017349243], [0.0, -0.07946893572807312, -1.262908935546875, 0.11880195140838623, 0.0629253089427948], [-0.5417174100875854, 0.09457648545503616, -0.5417174100875854, -0.4477871060371399, -0.17458638548851013], [-1.4764991998672485, 0.1663719266653061, -1.4764991998672485, -0.25861597061157227, -0.11267999559640884], [-2.0289053916931152, 0.03356125205755234, -2.0289053916931152, -0.03364919126033783, -0.016541555523872375], [-1.1938163042068481, 0.280501127243042, -1.1938163042068481, -0.715514600276947, -0.23496171832084656], [-1.5301952362060547, 0.18648573756217957, -1.5301952362060547, -0.283722460269928, -0.12187054753303528], [0.0, -0.1919032782316208, -1.9834764003753662, 0.1777465045452118, 0.09675097465515137], [-0.8996154069900513, 0.20745916664600372, -0.8996154069900513, -0.6906979084014893, -0.230608731508255], [-2.5258660316467285, 0.2600316107273102, -2.5258660316467285, -0.23289254307746887, -0.10294750332832336], [-1.6694430112838745, 0.45931074023246765, -1.6694430112838745, -1.4609787464141846, -0.2751281261444092], [-1.2339284420013428, 0.34358638525009155, -1.2339284420013428, -1.2666192054748535, -0.2784492075443268], [-1.4404211044311523, 0.39804717898368835, -1.4404211044311523, -1.142930269241333, -0.2763408422470093], [-1.2761428356170654, 0.3541521430015564, -1.2761428356170654, -1.3737478256225586, -0.2775176465511322], [-1.5850908756256104, 0.35015031695365906, -1.5850908756256104, -0.6397236585617065, -0.22090235352516174], [0.0, -0.27804017066955566, -2.5874781608581543, 0.19580358266830444, 0.10745604336261749], [-1.2494418621063232, 0.3447280526161194, -1.2494418621063232, -1.130099892616272, -0.27590563893318176], [-0.9907039403915405, 0.24238114058971405, -0.9907039403915405, -0.77649986743927, -0.24465547502040863], [0.0, -0.20399358868598938, -1.2859938144683838, 0.2786741256713867, 0.1586271971464157], [-2.6769440174102783, 0.2123429924249649, -2.6769440174102783, -0.17369258403778076, -0.07932291179895401], [-1.3597776889801025, 0.3602845370769501, -1.3597776889801025, -1.6638939380645752, -0.2649584114551544], [-1.7583158016204834, 0.4382784068584442, -1.7583158016204834, -1.8755720853805542, -0.24926035106182098]], "labels": ["gate-_in-_hook_pre_linear", "hook_post", "hook_pre_linear", "hook_pre", "swish"]}